Workbook
Name Slicer_Coffee_type: #N/A
Name Slicer_Year: #N/A

Sheet Pivot Table
A2: 1. What is the overall sales performance by coffee type over a specified period?.
A5: Total Sales | B5: Year
A6: Coffee type | B6: 2019 | C6: 2020 | D6: 2021 | E6: 2022 | F6: Grand Total
A7: Arabica | B7: 2926.63 | C7: 3356.415 | D7: 4045.63 | E7: 1439.82 | F7: 11768.495
A8: Excelsa | B8: 3481.46 | C8: 3663.41 | D8: 3469.64 | E8: 1691.93 | F8: 12306.44
A9: Liberica | B9: 3378.005 | C9: 2604.455 | D9: 3836.695 | E9: 2234.92 | F9: 12054.075
A10: Robusta | B10: 2401.07 | C10: 2493.265 | D10: 2414.145 | E10: 1696.765 | F10: 9005.245
A11: Grand Total | B11: 12187.165 | C11: 12117.545 | D11: 13766.11 | E11: 7063.435 | F11: 45134.255
A22: 2.How do sales vary across different countries.
A24: Country | B24: Total Sales
A25: Ireland | B25: 6696.865
A26: United Kingdom | B26: 2798.505
A27: United States | B27: 35638.885
A28: Grand Total | B28: 45134.255
A37: 3.What are the key cities contributing to total sales, and what is their respective performance?
A39: Cities | B39: Total Sales
A40: Birmingham | B40: 509.11
A41: Dallas | B41: 505.925
A42: Houston | B42: 819.77
A43: New York City | B43: 772.735
A44: Oklahoma City | B44: 475.17
A45: Philadelphia | B45: 511.235
A46: Portland | B46: 580.26
A47: Sacramento | B47: 627.75
A48: Toledo | B48: 774.185
A49: Washington | B49: 1066.92
A50: Grand Total | B50: 6643.06
A55: 4.Which roast type drives the highest sales,and how does each roast type compare?
A57: Roast types | B57: Total Sales
A58: Dark | B58: 13179.315
A59: Light | B59: 17354.465
A60: Medium | B60: 14600.475
A61: Grand Total | B61: 45134.255
A70: 5.How is the customer base distributed by country.
A72: Country | B72: Total no of customers
A73: Ireland | B73: 153
A74: United Kingdom | B74: 73
A75: United States | B75: 774
A76: Grand Total | B76: 1000
A85: 6.What is the distribution of customers by city?
A87: City | B87: Number of Customer Name
A88: Adare | B88: 2
A89: Akron | B89: 2
A90: Albany | B90: 5
A91: Albuquerque | B91: 1
A92: Alexandria | B92: 5
A93: Alhambra | B93: 1
A94: Allentown | B94: 3
A95: Amarillo | B95: 3
A96: Anaheim | B96: 2
A97: Anchorage | B97: 4
A98: Arklow | B98: 1
A99: Arlington | B99: 2
... A463: Grand Total | B463: 1000
A466: 7.How has the customer base evolved over the years?.
A468: Year | B468: Total no. of Customer
A469: 2019 | B469: 259
A470: 2020 | B470: 263
A471: 2021 | B471: 312
A472: 2022 | B472: 166
A473: Grand Total | B473: 1000
A479: 8.Who are the top 5 customers by purchase volumn or value?.
A481: Customer Name | B481: Number of Quantity
A482: Adrian Swaine | B482: 17
A483: Jimmy Dymoke | B483: 18
A484: Marja Urion | B484: 17
A485: Nealson Cuttler | B485: 18
A486: Terri Farra | B486: 22
A487: Grand Total | B487: 92
A493: 9.What are the monthly sales performance trends,and are there any seasonal patterns?.
A495: Month | B495: Total Sales
A496: August | B496: 2326.9
A497: December | B497: 3089.66
A498: May | B498: 3247.98
A499: January | B499: 3503.035
A500: November | B500: 3548.43
A501: September | B501: 3633.645
A502: October | B502: 3800.075
A503: July | B503: 3982.915
A504: February | B504: 4138.205
A505: April | B505: 4224.595
A506: March | B506: 4795.775
A507: June | B507: 4843.04
A508: Grand Total | B508: 45134.255
A511: 10.How does the monthly sales performance vary by coffee type?.
A513: Total Sales | B513: coffee type
A514: Month | B514: Arabica | C514: Excelsa | D514: Liberica | E514: Robusta | F514: Grand Total
A515: January | B515: 605.145 | C515: 677.72 | D515: 1611.07 | E515: 609.1 | F515: 3503.035
A516: February | B516: 1454.495 | C516: 976.41 | D516: 971.22 | E516: 736.08 | F516: 4138.205
A517: March | B517: 1051.48 | C517: 1264.14 | D517: 1469.81 | E517: 1010.345 | F517: 4795.775
A518: April | B518: 634.345 | C518: 1560.23 | D518: 1324.635 | E518: 705.385 | F518: 4224.595
A519: May | B519: 736.615 | C519: 970.33 | D519: 836.755 | E519: 704.28 | F519: 3247.98
A520: June | B520: 1357.99 | C520: 1598.195 | D520: 906.075 | E520: 980.78 | F520: 4843.04
A521: July | B521: 1131.935 | C521: 1141.555 | D521: 752.535 | E521: 956.89 | F521: 3982.915
A522: August | B522: 761.31 | C522: 478.59 | D522: 335.85 | E522: 751.15 | F522: 2326.9
A523: September | B523: 1145.79 | C523: 771.085 | D523: 699.77 | E523: 1017 | F523: 3633.645
A524: October | B524: 977.085 | C524: 937.33 | D524: 1241.16 | E524: 644.5 | F524: 3800.075
A525: November | B525: 1151.34 | C525: 771.38 | D525: 1235.745 | E525: 389.965 | F525: 3548.43
A526: December | B526: 760.965 | C526: 1159.475 | D526: 669.45 | E526: 499.77 | F526: 3089.66
A527: Grand Total | B527: 11768.495 | C527: 12306.44 | D527: 12054.075 | E527: 9005.245 | F527: 45134.255
...

Sheet Dashboard

Sheet WORKSHEET
A1: Order ID | B1: Order Date | C1: Year | D1: Month | E1: Customer ID | F1: Customer Name | G1: Email | H1: Phone number | I1: City | J1: Country | K1: Loyalty Card | L1: Product ID | M1: Coffee type | N1: Roast type | O1: Quantity | P1: Size | Q1: Unit Price | R1: Sales | S1: Profit | T1: Total Profit | U1: Profit Margin
A2: QE+A2:O991V-37451-860 | B2: 43713 | C2: =TEXT(B2,"yyyy") -> 2019 | D2: =TEXT(B2,"mmmm") -> September | E2: 17670-51384-MA | F2: =VLOOKUP(E2,Customers!$A$2:$I$1001,2,0) -> Aloisia Allner | G2: =VLOOKUP(E2,Customers!$A$2:$I$1001,3,0) -> aallner0@lulu.com | H2: =VLOOKUP(E2,Customers!$A$2:$I$1001,4,0) -> +1 (862) 817-0124 | I2: =VLOOKUP(E2,Customers!$A$2:$I$1001,6,0) -> Paterson | J2: =VLOOKUP(E2,Customers!$A$2:$I$1001,7,0) -> United States | K2: =VLOOKUP(E2,Customers!$A$2:$I$1001,9,0) -> Yes | L2: R-M-1 | M2: =VLOOKUP(L2,Products!$A$2:$G$49,2,0) -> Robusta | N2: =VLOOKUP(L2,Products!$A$2:$G$49,3,0) -> Medium | O2: 2 | P2: =INDEX([1]products!$A$1:$G$49,MATCH([1]orders!$D2,[1]products!$A$1:$A$49,0),MATCH([1]orders!K$1,[1]products!$A$1:$G$1,0)) -> 1 | Q2: =INDEX([1]products!$A$1:$G$49,MATCH([1]orders!$D2,[1]products!$A$1:$A$49,0),MATCH([1]orders!L$1,[1]products!$A$1:$G$1,0)) -> 9.95 | R2: =O2*Q2 -> 19.9 | S2: =VLOOKUP(L2,Products!$A$2:$G$49,7,0) -> 0.597 | T2: =O2*S2 -> 1.194 | U2: =T2/R2*100 -> 6
A3: QEV-37451-860 | B3: 43713 | C3: =TEXT(B3,"yyyy") -> 2019 | D3: =TEXT(B3,"mmmm") -> September | E3: 17670-51384-MA | F3: =VLOOKUP(E3,Customers!$A$2:$I$1001,2,0) -> Aloisia Allner | G3: =VLOOKUP(E3,Customers!$A$2:$I$1001,3,0) -> aallner0@lulu.com | H3: =VLOOKUP(E3,Customers!$A$2:$I$1001,4,0) -> +1 (862) 817-0124 | I3: =VLOOKUP(E3,Customers!$A$2:$I$1001,6,0) -> Paterson | J3: =VLOOKUP(E3,Customers!$A$2:$I$1001,7,0) -> United States | K3: =VLOOKUP(E3,Customers!$A$2:$I$1001,9,0) -> Yes | L3: E-M-0.5 | M3: =VLOOKUP(L3,Products!$A$2:$G$49,2,0) -> Excelsa | N3: =VLOOKUP(L3,Products!$A$2:$G$49,3,0) -> Medium | O3: 5 | P3: =INDEX([1]products!$A$1:$G$49,MATCH([1]orders!$D3,[1]products!$A$1:$A$49,0),MATCH([1]orders!K$1,[1]products!$A$1:$G$1,0)) -> 0.5 | Q3: =INDEX([1]products!$A$1:$G$49,MATCH([1]orders!$D3,[1]products!$A$1:$A$49,0),MATCH([1]orders!L$1,[1]products!$A$1:$G$1,0)) -> 8.25 | R3: =O3*Q3 -> 41.25 | S3: =VLOOKUP(L3,Products!$A$2:$G$49,7,0) -> 0.9075 | T3: =O3*S3 -> 4.5375 | U3: =T3/R3*100 -> 11
A4: FAA-43335-268 | B4: 44364 | C4: =TEXT(B4,"yyyy") -> 2021 | D4: =TEXT(B4,"mmmm") -> June | E4: 21125-22134-PX | F4: =VLOOKUP(E4,Customers!$A$2:$I$1001,2,0) -> Jami Redholes | G4: =VLOOKUP(E4,Customers!$A$2:$I$1001,3,0) -> jredholes2@tmall.com | H4: =VLOOKUP(E4,Customers!$A$2:$I$1001,4,0) -> +1 (210) 986-6806 | I4: =VLOOKUP(E4,Customers!$A$2:$I$1001,6,0) -> San Antonio | J4: =VLOOKUP(E4,Customers!$A$2:$I$1001,7,0) -> United States | K4: =VLOOKUP(E4,Customers!$A$2:$I$1001,9,0) -> Yes | L4: A-L-1 | M4: =VLOOKUP(L4,Products!$A$2:$G$49,2,0) -> Arabica | N4: =VLOOKUP(L4,Products!$A$2:$G$49,3,0) -> Light | O4: 1 | P4: =INDEX([1]products!$A$1:$G$49,MATCH([1]orders!$D4,[1]products!$A$1:$A$49,0),MATCH([1]orders!K$1,[1]products!$A$1:$G$1,0)) -> 1 | Q4: =INDEX([1]products!$A$1:$G$49,MATCH([1]orders!$D4,[1]products!$A$1:$A$49,0),MATCH([1]orders!L$1,[1]products!$A$1:$G$1,0)) -> 12.95 | R4: =O4*Q4 -> 12.95 | S4: =VLOOKUP(L4,Products!$A$2:$G$49,7,0) -> 1.1655 | T4: =O4*S4 -> 1.1655 | U4: =T4/R4*100 -> 9
A5: KAC-83089-793 | B5: 44392 | C5: =TEXT(B5,"yyyy") -> 2021 | D5: =TEXT(B5,"mmmm") -> July | E5: 23806-46781-OU | F5: =VLOOKUP(E5,Customers!$A$2:$I$1001,2,0) -> Christoffer O' Shea | G5: =VLOOKUP(E5,Customers!$A$2:$I$1001,3,0) -> UNKNOWN | H5: =VLOOKUP(E5,Customers!$A$2:$I$1001,4,0) -> +353 (698) 362-9201 | I5: =VLOOKUP(E5,Customers!$A$2:$I$1001,6,0) -> Cill Airne | J5: =VLOOKUP(E5,Customers!$A$2:$I$1001,7,0) -> Ireland | K5: =VLOOKUP(E5,Customers!$A$2:$I$1001,9,0) -> No | L5: E-M-1 | M5: =VLOOKUP(L5,Products!$A$2:$G$49,2,0) -> Excelsa | N5: =VLOOKUP(L5,Products!$A$2:$G$49,3,0) -> Medium | O5: 2 | P5: =INDEX([1]products!$A$1:$G$49,MATCH([1]orders!$D5,[1]products!$A$1:$A$49,0),MATCH([1]orders!K$1,[1]products!$A$1:$G$1,0)) -> 1 | Q5: =INDEX([1]products!$A$1:$G$49,MATCH([1]orders!$D5,[1]products!$A$1:$A$49,0),MATCH([1]orders!L$1,[1]products!$A$1:$G$1,0)) -> 13.75 | R5: =O5*Q5 -> 27.5 | S5: =VLOOKUP(L5,Products!$A$2:$G$49,7,0) -> 1.5125 | T5: =O5*S5 -> 3.025 | U5: =T5/R5*100 -> 11
A6: KAC-83089-793 | B6: 44392 | C6: =TEXT(B6,"yyyy") -> 2021 | D6: =TEXT(B6,"mmmm") -> July | E6: 23806-46781-OU | F6: =VLOOKUP(E6,Customers!$A$2:$I$1001,2,0) -> Christoffer O' Shea | G6: =VLOOKUP(E6,Customers!$A$2:$I$1001,3,0) -> UNKNOWN | H6: =VLOOKUP(E6,Customers!$A$2:$I$1001,4,0) -> +353 (698) 362-9201 | I6: =VLOOKUP(E6,Customers!$A$2:$I$1001,6,0) -> Cill Airne | J6: =VLOOKUP(E6,Customers!$A$2:$I$1001,7,0) -> Ireland | K6: =VLOOKUP(E6,Customers!$A$2:$I$1001,9,0) -> No | L6: R-L-2.5 | M6: =VLOOKUP(L6,Products!$A$2:$G$49,2,0) -> Robusta | N6: =VLOOKUP(L6,Products!$A$2:$G$49,3,0) -> Light | O6: 2 | P6: =INDEX([1]products!$A$1:$G$49,MATCH([1]orders!$D6,[1]products!$A$1:$A$49,0),MATCH([1]orders!K$1,[1]products!$A$1:$G$1,0)) -> 2.5 | Q6: =INDEX([1]products!$A$1:$G$49,MATCH([1]orders!$D6,[1]products!$A$1:$A$49,0),MATCH([1]orders!L$1,[1]products!$A$1:$G$1,0)) -> 27.485 | R6: =O6*Q6 -> 54.97 | S6: =VLOOKUP(L6,Products!$A$2:$G$49,7,0) -> 1.6491 | T6: =O6*S6 -> 3.2982 | U6: =T6/R6*100 -> 6
A7: CVP-18956-553 | B7: 44412 | C7: =TEXT(B7,"yyyy") -> 2021 | D7: =TEXT(B7,"mmmm") -> August | E7: 86561-91660-RB | F7: =VLOOKUP(E7,Customers!$A$2:$I$1001,2,0) -> Beryle Cottier | G7: =VLOOKUP(E7,Customers!$A$2:$I$1001,3,0) -> UNKNOWN | H7: =VLOOKUP(E7,Customers!$A$2:$I$1001,4,0) -> +1 (570) 289-7473 | I7: =VLOOKUP(E7,Customers!$A$2:$I$1001,6,0) -> Scranton | J7: =VLOOKUP(E7,Customers!$A$2:$I$1001,7,0) -> United States | K7: =VLOOKUP(E7,Customers!$A$2:$I$1001,9,0) -> No | L7: L-D-1 | M7: =VLOOKUP(L7,Products!$A$2:$G$49,2,0) -> Liberica | N7: =VLOOKUP(L7,Products!$A$2:$G$49,3,0) -> Dark | O7: 3 | P7: =INDEX([1]products!$A$1:$G$49,MATCH([1]orders!$D7,[1]products!$A$1:$A$49,0),MATCH([1]orders!K$1,[1]products!$A$1:$G$1,0)) -> 1 | Q7: =INDEX([1]products!$A$1:$G$49,MATCH([1]orders!$D7,[1]products!$A$1:$A$49,0),MATCH([1]orders!L$1,[1]products!$A$1:$G$1,0)) -> 12.95 | R7: =O7*Q7 -> 38.85 | S7: =VLOOKUP(L7,Products!$A$2:$G$49,7,0) -> 1.6835 | T7: =O7*S7 -> 5.0505 | U7: =T7/R7*100 -> 13 | X7: Sum of Total Profit
A8: IPP-31994-879 | B8: 44582 | C8: =TEXT(B8,"yyyy") -> 2022 | D8: =TEXT(B8,"mmmm") -> January | E8: 65223-29612-CB | F8: =VLOOKUP(E8,Customers!$A$2:$I$1001,2,0) -> Shaylynn Lobe | G8: =VLOOKUP(E8,Customers!$A$2:$I$1001,3,0) -> slobe6@nifty.com | H8: =VLOOKUP(E8,Customers!$A$2:$I$1001,4,0) -> +1 (937) 954-4541 | I8: =VLOOKUP(E8,Customers!$A$2:$I$1001,6,0) -> Dayton | J8: =VLOOKUP(E8,Customers!$A$2:$I$1001,7,0) -> United States | K8: =VLOOKUP(E8,Customers!$A$2:$I$1001,9,0) -> Yes | L8: E-D-0.5 | M8: =VLOOKUP(L8,Products!$A$2:$G$49,2,0) -> Excelsa | N8: =VLOOKUP(L8,Products!$A$2:$G$49,3,0) -> Dark | O8: 3 | P8: =INDEX([1]products!$A$1:$G$49,MATCH([1]orders!$D8,[1]products!$A$1:$A$49,0),MATCH([1]orders!K$1,[1]products!$A$1:$G$1,0)) -> 0.5 | Q8: =INDEX([1]products!$A$1:$G$49,MATCH([1]orders!$D8,[1]products!$A$1:$A$49,0),MATCH([1]orders!L$1,[1]products!$A$1:$G$1,0)) -> 7.29 | R8: =O8*Q8 -> 21.87 | S8: =VLOOKUP(L8,Products!$A$2:$G$49,7,0) -> 0.8019 | T8: =O8*S8 -> 2.4057 | U8: =T8/R8*100 -> 11 | X8: 4520.2174 | Y8: =GETPIVOTDATA("Total Profit",$X$7) -> 4520.2174
A9: SNZ-65340-705 | B9: 44701 | C9: =TEXT(B9,"yyyy") -> 2022 | D9: =TEXT(B9,"mmmm") -> May | E9: 21134-81676-FR | F9: =VLOOKUP(E9,Customers!$A$2:$I$1001,2,0) -> Melvin Wharfe | G9: =VLOOKUP(E9,Customers!$A$2:$I$1001,3,0) -> UNKNOWN | H9: =VLOOKUP(E9,Customers!$A$2:$I$1001,4,0) -> +353 (507) 574-3034 | I9: =VLOOKUP(E9,Customers!$A$2:$I$1001,6,0) -> Kill | J9: =VLOOKUP(E9,Customers!$A$2:$I$1001,7,0) -> Ireland | K9: =VLOOKUP(E9,Customers!$A$2:$I$1001,9,0) -> Yes | L9: L-L-0.2 | M9: =VLOOKUP(L9,Products!$A$2:$G$49,2,0) -> Liberica | N9: =VLOOKUP(L9,Products!$A$2:$G$49,3,0) -> Light | O9: 1 | P9: =INDEX([1]products!$A$1:$G$49,MATCH([1]orders!$D9,[1]products!$A$1:$A$49,0),MATCH([1]orders!K$1,[1]products!$A$1:$G$1,0)) -> 0.2 | Q9: =INDEX([1]products!$A$1:$G$49,MATCH([1]orders!$D9,[1]products!$A$1:$A$49,0),MATCH([1]orders!L$1,[1]products!$A$1:$G$1,0)) -> 4.755 | R9: =O9*Q9 -> 4.755 | S9: =VLOOKUP(L9,Products!$A$2:$G$49,7,0) -> 0.61815 | T9: =O9*S9 -> 0.61815 | U9: =T9/R9*100 -> 13
A10: EZT-46571-659 | B10: 43467 | C10: =TEXT(B10,"yyyy") -> 2019 | D10: =TEXT(B10,"mmmm") -> January | E10: 03396-68805-ZC | F10: =VLOOKUP(E10,Customers!$A$2:$I$1001,2,0) -> Guthrey Petracci | G10: =VLOOKUP(E10,Customers!$A$2:$I$1001,3,0) -> gpetracci8@livejournal.com | H10: =VLOOKUP(E10,Customers!$A$2:$I$1001,4,0) -> +1 (310) 868-1842 | I10: =VLOOKUP(E10,Customers!$A$2:$I$1001,6,0) -> Los Angeles | J10: =VLOOKUP(E10,Customers!$A$2:$I$1001,7,0) -> United States | K10: =VLOOKUP(E10,Customers!$A$2:$I$1001,9,0) -> No | L10: R-M-0.5 | M10: =VLOOKUP(L10,Products!$A$2:$G$49,2,0) -> Robusta | N10: =VLOOKUP(L10,Products!$A$2:$G$49,3,0) -> Medium | O10: 3 | P10: =INDEX([1]products!$A$1:$G$49,MATCH([1]orders!$D10,[1]products!$A$1:$A$49,0),MATCH([1]orders!K$1,[1]products!$A$1:$G$1,0)) -> 0.5 | Q10: =INDEX([1]products!$A$1:$G$49,MATCH([1]orders!$D10,[1]products!$A$1:$A$49,0),MATCH([1]orders!L$1,[1]products!$A$1:$G$1,0)) -> 5.97 | R10: =O10*Q10 -> 17.91 | S10: =VLOOKUP(L10,Products!$A$2:$G$49,7,0) -> 0.3582 | T10: =O10*S10 -> 1.0746 | U10: =T10/R10*100 -> 6
A11: NWQ-70061-912 | B11: 43713 | C11: =TEXT(B11,"yyyy") -> 2019 | D11: =TEXT(B11,"mmmm") -> September | E11: 61021-27840-ZN | F11: =VLOOKUP(E11,Customers!$A$2:$I$1001,2,0) -> Rodger Raven | G11: =VLOOKUP(E11,Customers!$A$2:$I$1001,3,0) -> rraven9@ed.gov | H11: =VLOOKUP(E11,Customers!$A$2:$I$1001,4,0) -> +1 (213) 263-0288 | I11: =VLOOKUP(E11,Customers!$A$2:$I$1001,6,0) -> Los Angeles | J11: =VLOOKUP(E11,Customers!$A$2:$I$1001,7,0) -> United States | K11: =VLOOKUP(E11,Customers!$A$2:$I$1001,9,0) -> No | L11: R-M-0.5 | M11: =VLOOKUP(L11,Products!$A$2:$G$49,2,0) -> Robusta | N11: =VLOOKUP(L11,Products!$A$2:$G$49,3,0) -> Medium | O11: 1 | P11: =INDEX([1]products!$A$1:$G$49,MATCH([1]orders!$D11,[1]products!$A$1:$A$49,0),MATCH([1]orders!K$1,[1]products!$A$1:$G$1,0)) -> 0.5 | Q11: =INDEX([1]products!$A$1:$G$49,MATCH([1]orders!$D11,[1]products!$A$1:$A$49,0),MATCH([1]orders!L$1,[1]products!$A$1:$G$1,0)) -> 5.97 | R11: =O11*Q11 -> 5.97 | S11: =VLOOKUP(L11,Products!$A$2:$G$49,7,0) -> 0.3582 | T11: =O11*S11 -> 0.3582 | U11: =T11/R11*100 -> 6 | X11: Count of Customer Name
A12: BKK-47233-845 | B12: 44263 | C12: =TEXT(B12,"yyyy") -> 2021 | D12: =TEXT(B12,"mmmm") -> March | E12: 76239-90137-UQ | F12: =VLOOKUP(E12,Customers!$A$2:$I$1001,2,0) -> Ferrell Ferber | G12: =VLOOKUP(E12,Customers!$A$2:$I$1001,3,0) -> fferbera@businesswire.com | H12: =VLOOKUP(E12,Customers!$A$2:$I$1001,4,0) -> +1 (408) 383-5302 | I12: =VLOOKUP(E12,Customers!$A$2:$I$1001,6,0) -> San Jose | J12: =VLOOKUP(E12,Customers!$A$2:$I$1001,7,0) -> United States | K12: =VLOOKUP(E12,Customers!$A$2:$I$1001,9,0) -> No | L12: A-D-1 | M12: =VLOOKUP(L12,Products!$A$2:$G$49,2,0) -> Arabica | N12: =VLOOKUP(L12,Products!$A$2:$G$49,3,0) -> Dark | O12: 4 | P12: =INDEX([1]products!$A$1:$G$49,MATCH([1]orders!$D12,[1]products!$A$1:$A$49,0),MATCH([1]orders!K$1,[1]products!$A$1:$G$1,0)) -> 1 | Q12: =INDEX([1]products!$A$1:$G$49,MATCH([1]orders!$D12,[1]products!$A$1:$A$49,0),MATCH([1]orders!L$1,[1]products!$A$1:$G$1,0)) -> 9.95 | R12: =O12*Q12 -> 39.8 | S12: =VLOOKUP(L12,Products!$A$2:$G$49,7,0) -> 0.8955 | T12: =O12*S12 -> 3.582 | U12: =T12/R12*100 -> 9 | X12: 1000 | Y12: =GETPIVOTDATA("Customer Name",$X$11) -> 1000
A13: VQR-01002-970 | B13: 44132 | C13: =TEXT(B13,"yyyy") -> 2020 | D13: =TEXT(B13,"mmmm") -> October | E13: 49315-21985-BB | F13: =VLOOKUP(E13,Customers!$A$2:$I$1001,2,0) -> Duky Phizackerly | G13: =VLOOKUP(E13,Customers!$A$2:$I$1001,3,0) -> dphizackerlyb@utexas.edu | H13: =VLOOKUP(E13,Customers!$A$2:$I$1001,4,0) -> +1 (408) 533-6012 | I13: =VLOOKUP(E13,Customers!$A$2:$I$1001,6,0) -> San Jose | J13: =VLOOKUP(E13,Customers!$A$2:$I$1001,7,0) -> United States | K13: =VLOOKUP(E13,Customers!$A$2:$I$1001,9,0) -> Yes | L13: E-L-2.5 | M13: =VLOOKUP(L13,Products!$A$2:$G$49,2,0) -> Excelsa | N13: =VLOOKUP(L13,Products!$A$2:$G$49,3,0) -> Light | O13: 5 | P13: =INDEX([1]products!$A$1:$G$49,MATCH([1]orders!$D13,[1]products!$A$1:$A$49,0),MATCH([1]orders!K$1,[1]products!$A$1:$G$1,0)) -> 2.5 | Q13: =INDEX([1]products!$A$1:$G$49,MATCH([1]orders!$D13,[1]products!$A$1:$A$49,0),MATCH([1]orders!L$1,[1]products!$A$1:$G$1,0)) -> 34.155 | R13: =O13*Q13 -> 170.775 | S13: =VLOOKUP(L13,Products!$A$2:$G$49,7,0) -> 3.75705 | T13: =O13*S13 -> 18.78525 | U13: =T13/R13*100 -> 11
A14: SZW-48378-399 | B14: 44744 | C14: =TEXT(B14,"yyyy") -> 2022 | D14: =TEXT(B14,"mmmm") -> July | E14: 34136-36674-OM | F14: =VLOOKUP(E14,Customers!$A$2:$I$1001,2,0) -> Rosaleen Scholar | G14: =VLOOKUP(E14,Customers!$A$2:$I$1001,3,0) -> rscholarc@nyu.edu | H14: =VLOOKUP(E14,Customers!$A$2:$I$1001,4,0) -> +1 (804) 420-0420 | I14: =VLOOKUP(E14,Customers!$A$2:$I$1001,6,0) -> Richmond | J14: =VLOOKUP(E14,Customers!$A$2:$I$1001,7,0) -> United States | K14: =VLOOKUP(E14,Customers!$A$2:$I$1001,9,0) -> No | L14: R-M-1 | M14: =VLOOKUP(L14,Products!$A$2:$G$49,2,0) -> Robusta | N14: =VLOOKUP(L14,Products!$A$2:$G$49,3,0) -> Medium | O14: 5 | P14: =INDEX([1]products!$A$1:$G$49,MATCH([1]orders!$D14,[1]products!$A$1:$A$49,0),MATCH([1]orders!K$1,[1]products!$A$1:$G$1,0)) -> 1 | Q14: =INDEX([1]products!$A$1:$G$49,MATCH([1]orders!$D14,[1]products!$A$1:$A$49,0),MATCH([1]orders!L$1,[1]products!$A$1:$G$1,0)) -> 9.95 | R14: =O14*Q14 -> 49.75 | S14: =VLOOKUP(L14,Products!$A$2:$G$49,7,0) -> 0.597 | T14: =O14*S14 -> 2.985 | U14: =T14/R14*100 -> 6
A15: ITA-87418-783 | B15: 43973 | C15: =TEXT(B15,"yyyy") -> 2020 | D15: =TEXT(B15,"mmmm") -> May | E15: 39396-12890-PE | F15: =VLOOKUP(E15,Customers!$A$2:$I$1001,2,0) -> Terence Vanyutin | G15: =VLOOKUP(E15,Customers!$A$2:$I$1001,3,0) -> tvanyutind@wix.com | H15: =VLOOKUP(E15,Customers!$A$2:$I$1001,4,0) -> UNKNOWN | I15: =VLOOKUP(E15,Customers!$A$2:$I$1001,6,0) -> Migrate | J15: =VLOOKUP(E15,Customers!$A$2:$I$1001,7,0) -> United States | K15: =VLOOKUP(E15,Customers!$A$2:$I$1001,9,0) -> No | L15: R-D-2.5 | M15: =VLOOKUP(L15,Products!$A$2:$G$49,2,0) -> Robusta | N15: =VLOOKUP(L15,Products!$A$2:$G$49,3,0) -> Dark | O15: 2 | P15: =INDEX([1]products!$A$1:$G$49,MATCH([1]orders!$D15,[1]products!$A$1:$A$49,0),MATCH([1]orders!K$1,[1]products!$A$1:$G$1,0)) -> 2.5 | Q15: =INDEX([1]products!$A$1:$G$49,MATCH([1]orders!$D15,[1]products!$A$1:$A$49,0),MATCH([1]orders!L$1,[1]products!$A$1:$G$1,0)) -> 20.585 | R15: =O15*Q15 -> 41.17 | S15: =VLOOKUP(L15,Products!$A$2:$G$49,7,0) -> 1.2351 | T15: =O15*S15 -> 2.4702 | U15: =T15/R15*100 -> 6
A16: GNZ-46006-527 | B16: 44656 | C16: =TEXT(B16,"yyyy") -> 2022 | D16: =TEXT(B16,"mmmm") -> April | E16: 95875-73336-RG | F16: =VLOOKUP(E16,Customers!$A$2:$I$1001,2,0) -> Patrice Trobe | G16: =VLOOKUP(E16,Customers!$A$2:$I$1001,3,0) -> ptrobee@wunderground.com | H16: =VLOOKUP(E16,Customers!$A$2:$I$1001,4,0) -> +1 (314) 240-7896 | I16: =VLOOKUP(E16,Customers!$A$2:$I$1001,6,0) -> Saint Louis | J16: =VLOOKUP(E16,Customers!$A$2:$I$1001,7,0) -> United States | K16: =VLOOKUP(E16,Customers!$A$2:$I$1001,9,0) -> Yes | L16: L-D-0.2 | M16: =VLOOKUP(L16,Products!$A$2:$G$49,2,0) -> Liberica | N16: =VLOOKUP(L16,Products!$A$2:$G$49,3,0) -> Dark | O16: 3 | P16: =INDEX([1]products!$A$1:$G$49,MATCH([1]orders!$D16,[1]products!$A$1:$A$49,0),MATCH([1]orders!K$1,[1]products!$A$1:$G$1,0)) -> 0.2 | Q16: =INDEX([1]products!$A$1:$G$49,MATCH([1]orders!$D16,[1]products!$A$1:$A$49,0),MATCH([1]orders!L$1,[1]products!$A$1:$G$1,0)) -> 3.885 | R16: =O16*Q16 -> 11.655 | S16: =VLOOKUP(L16,Products!$A$2:$G$49,7,0) -> 0.50505 | T16: =O16*S16 -> 1.51515 | U16: =T16/R16*100 -> 13
A17: FYQ-78248-319 | B17: 44719 | C17: =TEXT(B17,"yyyy") -> 2022 | D17: =TEXT(B17,"mmmm") -> June | E17: 25473-43727-BY | F17: =VLOOKUP(E17,Customers!$A$2:$I$1001,2,0) -> Llywellyn Oscroft | G17: =VLOOKUP(E17,Customers!$A$2:$I$1001,3,0) -> loscroftf@ebay.co.uk | H17: =VLOOKUP(E17,Customers!$A$2:$I$1001,4,0) -> UNKNOWN | I17: =VLOOKUP(E17,Customers!$A$2:$I$1001,6,0) -> Philadelphia | J17: =VLOOKUP(E17,Customers!$A$2:$I$1001,7,0) -> United States | K17: =VLOOKUP(E17,Customers!$A$2:$I$1001,9,0) -> No | L17: R-M-2.5 | M17: =VLOOKUP(L17,Products!$A$2:$G$49,2,0) -> Robusta | N17: =VLOOKUP(L17,Products!$A$2:$G$49,3,0) -> Medium | O17: 5 | P17: =INDEX([1]products!$A$1:$G$49,MATCH([1]orders!$D17,[1]products!$A$1:$A$49,0),MATCH([1]orders!K$1,[1]products!$A$1:$G$1,0)) -> 2.5 | Q17: =INDEX([1]products!$A$1:$G$49,MATCH([1]orders!$D17,[1]products!$A$1:$A$49,0),MATCH([1]orders!L$1,[1]products!$A$1:$G$1,0)) -> 22.885 | R17: =O17*Q17 -> 114.425 | S17: =VLOOKUP(L17,Products!$A$2:$G$49,7,0) -> 1.3731 | T17: =O17*S17 -> 6.8655 | U17: =T17/R17*100 -> 6
A18: VAU-44387-624 | B18: 43544 | C18: =TEXT(B18,"yyyy") -> 2019 | D18: =TEXT(B18,"mmmm") -> March | E18: 99643-51048-IQ | F18: =VLOOKUP(E18,Customers!$A$2:$I$1001,2,0) -> Minni Alabaster | G18: =VLOOKUP(E18,Customers!$A$2:$I$1001,3,0) -> malabasterg@hexun.com | H18: =VLOOKUP(E18,Customers!$A$2:$I$1001,4,0) -> +1 (971) 483-6255 | I18: =VLOOKUP(E18,Customers!$A$2:$I$1001,6,0) -> Portland | J18: =VLOOKUP(E18,Customers!$A$2:$I$1001,7,0) -> United States | K18: =VLOOKUP(E18,Customers!$A$2:$I$1001,9,0) -> No | L18: A-M-0.2 | M18: =VLOOKUP(L18,Products!$A$2:$G$49,2,0) -> Arabica | N18: =VLOOKUP(L18,Products!$A$2:$G$49,3,0) -> Medium | O18: 6 | P18: =INDEX([1]products!$A$1:$G$49,MATCH([1]orders!$D18,[1]products!$A$1:$A$49,0),MATCH([1]orders!K$1,[1]products!$A$1:$G$1,0)) -> 0.2 | Q18: =INDEX([1]products!$A$1:$G$49,MATCH([1]orders!$D18,[1]products!$A$1:$A$49,0),MATCH([1]orders!L$1,[1]products!$A$1:$G$1,0)) -> 3.375 | R18: =O18*Q18 -> 20.25 | S18: =VLOOKUP(L18,Products!$A$2:$G$49,7,0) -> 0.30375 | T18: =O18*S18 -> 1.8225 | U18: =T18/R18*100 -> 9
A19: RDW-33155-159 | B19: 43757 | C19: =TEXT(B19,"yyyy") -> 2019 | D19: =TEXT(B19,"mmmm") -> October | E19: 62173-15287-CU | F19: =VLOOKUP(E19,Customers!$A$2:$I$1001,2,0) -> Rhianon Broxup | G19: =VLOOKUP(E19,Customers!$A$2:$I$1001,3,0) -> rbroxuph@jimdo.com | H19: =VLOOKUP(E19,Customers!$A$2:$I$1001,4,0) -> +1 (713) 663-1338 | I19: =VLOOKUP(E19,Customers!$A$2:$I$1001,6,0) -> Houston | J19: =VLOOKUP(E19,Customers!$A$2:$I$1001,7,0) -> United States | K19: =VLOOKUP(E19,Customers!$A$2:$I$1001,9,0) -> No | L19: A-L-1 | M19: =VLOOKUP(L19,Products!$A$2:$G$49,2,0) -> Arabica | N19: =VLOOKUP(L19,Products!$A$2:$G$49,3,0) -> Light | O19: 6 | P19: =INDEX([1]products!$A$1:$G$49,MATCH([1]orders!$D19,[1]products!$A$1:$A$49,0),MATCH([1]orders!K$1,[1]products!$A$1:$G$1,0)) -> 1 | Q19: =INDEX([1]products!$A$1:$G$49,MATCH([1]orders!$D19,[1]products!$A$1:$A$49,0),MATCH([1]orders!L$1,[1]products!$A$1:$G$1,0)) -> 12.95 | R19: =O19*Q19 -> 77.7 | S19: =VLOOKUP(L19,Products!$A$2:$G$49,7,0) -> 1.1655 | T19: =O19*S19 -> 6.993 | U19: =T19/R19*100 -> 9
A20: TDZ-59011-211 | B20: 43629 | C20: =TEXT(B20,"yyyy") -> 2019 | D20: =TEXT(B20,"mmmm") -> June | E20: 57611-05522-ST | F20: =VLOOKUP(E20,Customers!$A$2:$I$1001,2,0) -> Pall Redford | G20: =VLOOKUP(E20,Customers!$A$2:$I$1001,3,0) -> predfordi@ow.ly | H20: =VLOOKUP(E20,Customers!$A$2:$I$1001,4,0) -> UNKNOWN | I20: =VLOOKUP(E20,Customers!$A$2:$I$1001,6,0) -> Caherconlish | J20: =VLOOKUP(E20,Customers!$A$2:$I$1001,7,0) -> Ireland | K20: =VLOOKUP(E20,Customers!$A$2:$I$1001,9,0) -> Yes | L20: R-D-2.5 | M20: =VLOOKUP(L20,Products!$A$2:$G$49,2,0) -> Robusta | N20: =VLOOKUP(L20,Products!$A$2:$G$49,3,0) -> Dark | O20: 4 | P20: =INDEX([1]products!$A$1:$G$49,MATCH([1]orders!$D20,[1]products!$A$1:$A$49,0),MATCH([1]orders!K$1,[1]products!$A$1:$G$1,0)) -> 2.5 | Q20: =INDEX([1]products!$A$1:$G$49,MATCH([1]orders!$D20,[1]products!$A$1:$A$49,0),MATCH([1]orders!L$1,[1]products!$A$1:$G$1,0)) -> 20.585 | R20: =O20*Q20 -> 82.34 | S20: =VLOOKUP(L20,Products!$A$2:$G$49,7,0) -> 1.2351 | T20: =O20*S20 -> 4.9404 | U20: =T20/R20*100 -> 6
A21: IDU-25793-399 | B21: 44169 | C21: =TEXT(B21,"yyyy") -> 2020 | D21: =TEXT(B21,"mmmm") -> December | E21: 76664-37050-DT | F21: =VLOOKUP(E21,Customers!$A$2:$I$1001,2,0) -> Aurea Corradino | G21: =VLOOKUP(E21,Customers!$A$2:$I$1001,3,0) -> acorradinoj@harvard.edu | H21: =VLOOKUP(E21,Customers!$A$2:$I$1001,4,0) -> +1 (646) 202-5965 | I21: =VLOOKUP(E21,Customers!$A$2:$I$1001,6,0) -> New York City | J21: =VLOOKUP(E21,Customers!$A$2:$I$1001,7,0) -> United States | K21: =VLOOKUP(E21,Customers!$A$2:$I$1001,9,0) -> Yes | L21: A-M-0.2 | M21: =VLOOKUP(L21,Products!$A$2:$G$49,2,0) -> Arabica | N21: =VLOOKUP(L21,Products!$A$2:$G$49,3,0) -> Medium | O21: 5 | P21: =INDEX([1]products!$A$1:$G$49,MATCH([1]orders!$D21,[1]products!$A$1:$A$49,0),MATCH([1]orders!K$1,[1]products!$A$1:$G$1,0)) -> 0.2 | Q21: =INDEX([1]products!$A$1:$G$49,MATCH([1]orders!$D21,[1]products!$A$1:$A$49,0),MATCH([1]orders!L$1,[1]products!$A$1:$G$1,0)) -> 3.375 | R21: =O21*Q21 -> 16.875 | S21: =VLOOKUP(L21,Products!$A$2:$G$49,7,0) -> 0.30375 | T21: =O21*S21 -> 1.51875 | U21: =T21/R21*100 -> 9
A22: IDU-25793-399 | B22: 44169 | C22: =TEXT(B22,"yyyy") -> 2020 | D22: =TEXT(B22,"mmmm") -> December | E22: 76664-37050-DT | F22: =VLOOKUP(E22,Customers!$A$2:$I$1001,2,0) -> Aurea Corradino | G22: =VLOOKUP(E22,Customers!$A$2:$I$1001,3,0) -> acorradinoj@harvard.edu | H22: =VLOOKUP(E22,Customers!$A$2:$I$1001,4,0) -> +1 (646) 202-5965 | I22: =VLOOKUP(E22,Customers!$A$2:$I$1001,6,0) -> New York City | J22: =VLOOKUP(E22,Customers!$A$2:$I$1001,7,0) -> United States | K22: =VLOOKUP(E22,Customers!$A$2:$I$1001,9,0) -> Yes | L22: E-D-0.2 | M22: =VLOOKUP(L22,Products!$A$2:$G$49,2,0) -> Excelsa | N22: =VLOOKUP(L22,Products!$A$2:$G$49,3,0) -> Dark | O22: 4 | P22: =INDEX([1]products!$A$1:$G$49,MATCH([1]orders!$D22,[1]products!$A$1:$A$49,0),MATCH([1]orders!K$1,[1]products!$A$1:$G$1,0)) -> 0.2 | Q22: =INDEX([1]products!$A$1:$G$49,MATCH([1]orders!$D22,[1]products!$A$1:$A$49,0),MATCH([1]orders!L$1,[1]products!$A$1:$G$1,0)) -> 3.645 | R22: =O22*Q22 -> 14.58 | S22: =VLOOKUP(L22,Products!$A$2:$G$49,7,0) -> 0.40095 | T22: =O22*S22 -> 1.6038 | U22: =T22/R22*100 -> 11
A23: NUO-20013-488 | B23: 44169 | C23: =TEXT(B23,"yyyy") -> 2020 | D23: =TEXT(B23,"mmmm") -> December | E23: 03090-88267-BQ | F23: =VLOOKUP(E23,Customers!$A$2:$I$1001,2,0) -> Avrit Davidowsky | G23: =VLOOKUP(E23,Customers!$A$2:$I$1001,3,0) -> adavidowskyl@netvibes.com | H23: =VLOOKUP(E23,Customers!$A$2:$I$1001,4,0) -> +1 (616) 481-9962 | I23: =VLOOKUP(E23,Customers!$A$2:$I$1001,6,0) -> Grand Rapids | J23: =VLOOKUP(E23,Customers!$A$2:$I$1001,7,0) -> United States | K23: =VLOOKUP(E23,Customers!$A$2:$I$1001,9,0) -> No | L23: A-D-0.2 | M23: =VLOOKUP(L23,Products!$A$2:$G$49,2,0) -> Arabica | N23: =VLOOKUP(L23,Products!$A$2:$G$49,3,0) -> Dark | O23: 6 | P23: =INDEX([1]products!$A$1:$G$49,MATCH([1]orders!$D23,[1]products!$A$1:$A$49,0),MATCH([1]orders!K$1,[1]products!$A$1:$G$1,0)) -> 0.2 | Q23: =INDEX([1]products!$A$1:$G$49,MATCH([1]orders!$D23,[1]products!$A$1:$A$49,0),MATCH([1]orders!L$1,[1]products!$A$1:$G$1,0)) -> 2.985 | R23: =O23*Q23 -> 17.91 | S23: =VLOOKUP(L23,Products!$A$2:$G$49,7,0) -> 0.26865 | T23: =O23*S23 -> 1.6119 | U23: =T23/R23*100 -> 9
A24: UQU-65630-479 | B24: 44218 | C24: =TEXT(B24,"yyyy") -> 2021 | D24: =TEXT(B24,"mmmm") -> January | E24: 37651-47492-NC | F24: =VLOOKUP(E24,Customers!$A$2:$I$1001,2,0) -> Annabel Antuk | G24: =VLOOKUP(E24,Customers!$A$2:$I$1001,3,0) -> aantukm@kickstarter.com | H24: =VLOOKUP(E24,Customers!$A$2:$I$1001,4,0) -> +1 (941) 740-6268 | I24: =VLOOKUP(E24,Customers!$A$2:$I$1001,6,0) -> Punta Gorda | J24: =VLOOKUP(E24,Customers!$A$2:$I$1001,7,0) -> United States | K24: =VLOOKUP(E24,Customers!$A$2:$I$1001,9,0) -> Yes | L24: R-M-2.5 | M24: =VLOOKUP(L24,Products!$A$2:$G$49,2,0) -> Robusta | N24: =VLOOKUP(L24,Products!$A$2:$G$49,3,0) -> Medium | O24: 4 | P24: =INDEX([1]products!$A$1:$G$49,MATCH([1]orders!$D24,[1]products!$A$1:$A$49,0),MATCH([1]orders!K$1,[1]products!$A$1:$G$1,0)) -> 2.5 | Q24: =INDEX([1]products!$A$1:$G$49,MATCH([1]orders!$D24,[1]products!$A$1:$A$49,0),MATCH([1]orders!L$1,[1]products!$A$1:$G$1,0)) -> 22.885 | R24: =O24*Q24 -> 91.54 | S24: =VLOOKUP(L24,Products!$A$2:$G$49,7,0) -> 1.3731 | T24: =O24*S24 -> 5.4924 | U24: =T24/R24*100 -> 6
... A1001: IRV-20769-219 | B1001: 44119 | C1001: =TEXT(B1001,"yyyy") -> 2020 | D1001: =TEXT(B1001,"mmmm") -> October | E1001: 77131-58092-GE | F1001: =VLOOKUP(E1001,Customers!$A$2:$I$1001,2,0) -> Vidovic Antonelli | G1001: =VLOOKUP(E1001,Customers!$A$2:$I$1001,3,0) -> UNKNOWN | H1001: =VLOOKUP(E1001,Customers!$A$2:$I$1001,4,0) -> +44 (810) 927-9266 | I1001: =VLOOKUP(E1001,Customers!$A$2:$I$1001,6,0) -> London | J1001: =VLOOKUP(E1001,Customers!$A$2:$I$1001,7,0) -> United Kingdom | K1001: =VLOOKUP(E1001,Customers!$A$2:$I$1001,9,0) -> Yes | L1001: E-M-0.2 | M1001: =VLOOKUP(L1001,Products!$A$2:$G$49,2,0) -> Excelsa | N1001: =VLOOKUP(L1001,Products!$A$2:$G$49,3,0) -> Medium | O1001: 3 | P1001: =INDEX([1]products!$A$1:$G$49,MATCH([1]orders!$D1001,[1]products!$A$1:$A$49,0),MATCH([1]orders!K$1,[1]products!$A$1:$G$1,0)) -> 0.2 | Q1001: =INDEX([1]products!$A$1:$G$49,MATCH([1]orders!$D1001,[1]products!$A$1:$A$49,0),MATCH([1]orders!L$1,[1]products!$A$1:$G$1,0)) -> 4.125 | R1001: =O1001*Q1001 -> 12.375 | S1001: =VLOOKUP(L1001,Products!$A$2:$G$49,7,0) -> 0.45375 | T1001: =O1001*S1001 -> 1.36125 | U1001: =T1001/R1001*100 -> 11

Sheet Orders
A1: Order ID | B1: Order Date | C1: Customer ID | D1: Product ID | E1: Quantity | F1: Size | G1: Unit Price | H1: Sales
A2: QEV-37451-860 | B2: 43713 | C2: 17670-51384-MA | D2: R-M-1 | E2: 2 | F2: =INDEX([1]products!$A$1:$G$49,MATCH([1]orders!$D2,[1]products!$A$1:$A$49,0),MATCH([1]orders!K$1,[1]products!$A$1:$G$1,0)) -> 1 | G2: =INDEX([1]products!$A$1:$G$49,MATCH([1]orders!$D2,[1]products!$A$1:$A$49,0),MATCH([1]orders!L$1,[1]products!$A$1:$G$1,0)) -> 9.95 | H2: =E2*G2 -> 19.9
A3: QEV-37451-860 | B3: 43713 | C3: 17670-51384-MA | D3: E-M-0.5 | E3: 5 | F3: =INDEX([1]products!$A$1:$G$49,MATCH([1]orders!$D3,[1]products!$A$1:$A$49,0),MATCH([1]orders!K$1,[1]products!$A$1:$G$1,0)) -> 0.5 | G3: =INDEX([1]products!$A$1:$G$49,MATCH([1]orders!$D3,[1]products!$A$1:$A$49,0),MATCH([1]orders!L$1,[1]products!$A$1:$G$1,0)) -> 8.25 | H3: =E3*G3 -> 41.25
A4: FAA-43335-268 | B4: 44364 | C4: 21125-22134-PX | D4: A-L-1 | E4: 1 | F4: =INDEX([1]products!$A$1:$G$49,MATCH([1]orders!$D4,[1]products!$A$1:$A$49,0),MATCH([1]orders!K$1,[1]products!$A$1:$G$1,0)) -> 1 | G4: =INDEX([1]products!$A$1:$G$49,MATCH([1]orders!$D4,[1]products!$A$1:$A$49,0),MATCH([1]orders!L$1,[1]products!$A$1:$G$1,0)) -> 12.95 | H4: =E4*G4 -> 12.95
A5: KAC-83089-793 | B5: 44392 | C5: 23806-46781-OU | D5: E-M-1 | E5: 2 | F5: =INDEX([1]products!$A$1:$G$49,MATCH([1]orders!$D5,[1]products!$A$1:$A$49,0),MATCH([1]orders!K$1,[1]products!$A$1:$G$1,0)) -> 1 | G5: =INDEX([1]products!$A$1:$G$49,MATCH([1]orders!$D5,[1]products!$A$1:$A$49,0),MATCH([1]orders!L$1,[1]products!$A$1:$G$1,0)) -> 13.75 | H5: =E5*G5 -> 27.5
A6: KAC-83089-793 | B6: 44392 | C6: 23806-46781-OU | D6: R-L-2.5 | E6: 2 | F6: =INDEX([1]products!$A$1:$G$49,MATCH([1]orders!$D6,[1]products!$A$1:$A$49,0),MATCH([1]orders!K$1,[1]products!$A$1:$G$1,0)) -> 2.5 | G6: =INDEX([1]products!$A$1:$G$49,MATCH([1]orders!$D6,[1]products!$A$1:$A$49,0),MATCH([1]orders!L$1,[1]products!$A$1:$G$1,0)) -> 27.485 | H6: =E6*G6 -> 54.97
A7: CVP-18956-553 | B7: 44412 | C7: 86561-91660-RB | D7: L-D-1 | E7: 3 | F7: =INDEX([1]products!$A$1:$G$49,MATCH([1]orders!$D7,[1]products!$A$1:$A$49,0),MATCH([1]orders!K$1,[1]products!$A$1:$G$1,0)) -> 1 | G7: =INDEX([1]products!$A$1:$G$49,MATCH([1]orders!$D7,[1]products!$A$1:$A$49,0),MATCH([1]orders!L$1,[1]products!$A$1:$G$1,0)) -> 12.95 | H7: =E7*G7 -> 38.85
A8: IPP-31994-879 | B8: 44582 | C8: 65223-29612-CB | D8: E-D-0.5 | E8: 3 | F8: =INDEX([1]products!$A$1:$G$49,MATCH([1]orders!$D8,[1]products!$A$1:$A$49,0),MATCH([1]orders!K$1,[1]products!$A$1:$G$1,0)) -> 0.5 | G8: =INDEX([1]products!$A$1:$G$49,MATCH([1]orders!$D8,[1]products!$A$1:$A$49,0),MATCH([1]orders!L$1,[1]products!$A$1:$G$1,0)) -> 7.29 | H8: =E8*G8 -> 21.87
A9: SNZ-65340-705 | B9: 44701 | C9: 21134-81676-FR | D9: L-L-0.2 | E9: 1 | F9: =INDEX([1]products!$A$1:$G$49,MATCH([1]orders!$D9,[1]products!$A$1:$A$49,0),MATCH([1]orders!K$1,[1]products!$A$1:$G$1,0)) -> 0.2 | G9: =INDEX([1]products!$A$1:$G$49,MATCH([1]orders!$D9,[1]products!$A$1:$A$49,0),MATCH([1]orders!L$1,[1]products!$A$1:$G$1,0)) -> 4.755 | H9: =E9*G9 -> 4.755
A10: EZT-46571-659 | B10: 43467 | C10: 03396-68805-ZC | D10: R-M-0.5 | E10: 3 | F10: =INDEX([1]products!$A$1:$G$49,MATCH([1]orders!$D10,[1]products!$A$1:$A$49,0),MATCH([1]orders!K$1,[1]products!$A$1:$G$1,0)) -> 0.5 | G10: =INDEX([1]products!$A$1:$G$49,MATCH([1]orders!$D10,[1]products!$A$1:$A$49,0),MATCH([1]orders!L$1,[1]products!$A$1:$G$1,0)) -> 5.97 | H10: =E10*G10 -> 17.91
A11: NWQ-70061-912 | B11: 43713 | C11: 61021-27840-ZN | D11: R-M-0.5 | E11: 1 | F11: =INDEX([1]products!$A$1:$G$49,MATCH([1]orders!$D11,[1]products!$A$1:$A$49,0),MATCH([1]orders!K$1,[1]products!$A$1:$G$1,0)) -> 0.5 | G11: =INDEX([1]products!$A$1:$G$49,MATCH([1]orders!$D11,[1]products!$A$1:$A$49,0),MATCH([1]orders!L$1,[1]products!$A$1:$G$1,0)) -> 5.97 | H11: =E11*G11 -> 5.97
A12: BKK-47233-845 | B12: 44263 | C12: 76239-90137-UQ | D12: A-D-1 | E12: 4 | F12: =INDEX([1]products!$A$1:$G$49,MATCH([1]orders!$D12,[1]products!$A$1:$A$49,0),MATCH([1]orders!K$1,[1]products!$A$1:$G$1,0)) -> 1 | G12: =INDEX([1]products!$A$1:$G$49,MATCH([1]orders!$D12,[1]products!$A$1:$A$49,0),MATCH([1]orders!L$1,[1]products!$A$1:$G$1,0)) -> 9.95 | H12: =E12*G12 -> 39.8
A13: VQR-01002-970 | B13: 44132 | C13: 49315-21985-BB | D13: E-L-2.5 | E13: 5 | F13: =INDEX([1]products!$A$1:$G$49,MATCH([1]orders!$D13,[1]products!$A$1:$A$49,0),MATCH([1]orders!K$1,[1]products!$A$1:$G$1,0)) -> 2.5 | G13: =INDEX([1]products!$A$1:$G$49,MATCH([1]orders!$D13,[1]products!$A$1:$A$49,0),MATCH([1]orders!L$1,[1]products!$A$1:$G$1,0)) -> 34.155 | H13: =E13*G13 -> 170.775
... A1001: IRV-20769-219 | B1001: 44119 | C1001: 77131-58092-GE | D1001: E-M-0.2 | E1001: 3 | F1001: =INDEX([1]products!$A$1:$G$49,MATCH([1]orders!$D1001,[1]products!$A$1:$A$49,0),MATCH([1]orders!K$1,[1]products!$A$1:$G$1,0)) -> 0.2 | G1001: =INDEX([1]products!$A$1:$G$49,MATCH([1]orders!$D1001,[1]products!$A$1:$A$49,0),MATCH([1]orders!L$1,[1]products!$A$1:$G$1,0)) -> 4.125 | H1001: =E1001*G1001 -> 12.375

Sheet Customers
A1: Customer ID | B1: Customer Name | C1: Email | D1: Phone Number | E1: Address Line 1 | F1: City | G1: Country | H1: Postcode | I1: Loyalty Card
A2: 17670-51384-MA | B2: Aloisia Allner | C2: aallner0@lulu.com | D2: +1 (862) 817-0124 | E2: 57999 Pepper Wood Alley | F2: Paterson | G2: United States | H2: 7505 | I2: Yes
A3: 73342-18763-UW | B3: Piotr Bote | C3: pbote1@yelp.com | D3: +353 (913) 396-4653 | E3: 2112 Ridgeway Hill | F3: Crumlin | G3: Ireland | H3: D6W | I3: No
A4: 21125-22134-PX | B4: Jami Redholes | C4: jredholes2@tmall.com | D4: +1 (210) 986-6806 | E4: 5214 Bartillon Park | F4: San Antonio | G4: United States | H4: 78205 | I4: Yes
A5: 71253-00052-RN | B5: Dene Azema | C5: dazema3@facebook.com | D5: +1 (217) 418-0714 | E5: 27 Maywood Place | F5: Springfield | G5: United States | H5: 62711 | I5: Yes
A6: 23806-46781-OU | B6: Christoffer O' Shea | C6: UNKNOWN | D6: +353 (698) 362-9201 | E6: 38980 Manitowish Junction | F6: Cill Airne | G6: Ireland | H6: N41 | I6: No
A7: 86561-91660-RB | B7: Beryle Cottier | C7: UNKNOWN | D7: +1 (570) 289-7473 | E7: 2651 Stoughton Place | F7: Scranton | G7: United States | H7: 18505 | I7: No
A8: 65223-29612-CB | B8: Shaylynn Lobe | C8: slobe6@nifty.com | D8: +1 (937) 954-4541 | E8: 7005 Mariners Cove Place | F8: Dayton | G8: United States | H8: 45440 | I8: Yes
A9: 21134-81676-FR | B9: Melvin Wharfe | C9: UNKNOWN | D9: +353 (507) 574-3034 | E9: 7 Straubel Road | F9: Kill | G9: Ireland | H9: P24 | I9: Yes
A10: 03396-68805-ZC | B10: Guthrey Petracci | C10: gpetracci8@livejournal.com | D10: +1 (310) 868-1842 | E10: 949 Paget Parkway | F10: Los Angeles | G10: United States | H10: 90045 | I10: No
A11: 61021-27840-ZN | B11: Rodger Raven | C11: rraven9@ed.gov | D11: +1 (213) 263-0288 | E11: 1 Reinke Avenue | F11: Los Angeles | G11: United States | H11: 90065 | I11: No
A12: 76239-90137-UQ | B12: Ferrell Ferber | C12: fferbera@businesswire.com | D12: +1 (408) 383-5302 | E12: 68 High Crossing Court | F12: San Jose | G12: United States | H12: 95160 | I12: No
A13: 49315-21985-BB | B13: Duky Phizackerly | C13: dphizackerlyb@utexas.edu | D13: +1 (408) 533-6012 | E13: 28643 Bluejay Crossing | F13: San Jose | G13: United States | H13: 95194 | I13: Yes
A14: 34136-36674-OM | B14: Rosaleen Scholar | C14: rscholarc@nyu.edu | D14: +1 (804) 420-0420 | E14: 80915 Montana Park | F14: Richmond | G14: United States | H14: 23285 | I14: No
A15: 39396-12890-PE | B15: Terence Vanyutin | C15: tvanyutind@wix.com | D15: UNKNOWN | E15: 331 Bunting Hill | F15: Migrate | G15: United States | H15: 41905 | I15: No
A16: 95875-73336-RG | B16: Patrice Trobe | C16: ptrobee@wunderground.com | D16: +1 (314) 240-7896 | E16: 827 Declaration Plaza | F16: Saint Louis | G16: United States | H16: 63131 | I16: Yes
A17: 25473-43727-BY | B17: Llywellyn Oscroft | C17: loscroftf@ebay.co.uk | D17: UNKNOWN | E17: 022 Roth Place | F17: Philadelphia | G17: United States | H17: 19172 | I17: No
A18: 99643-51048-IQ | B18: Minni Alabaster | C18: malabasterg@hexun.com | D18: +1 (971) 483-6255 | E18: 3 Charing Cross Trail | F18: Portland | G18: United States | H18: 97271 | I18: No
A19: 62173-15287-CU | B19: Rhianon Broxup | C19: rbroxuph@jimdo.com | D19: +1 (713) 663-1338 | E19: 83517 Thierer Court | F19: Houston | G19: United States | H19: 77240 | I19: No
A20: 57611-05522-ST | B20: Pall Redford | C20: predfordi@ow.ly | D20: UNKNOWN | E20: 7337 Hayes Junction | F20: Caherconlish | G20: Ireland | H20: F45 | I20: Yes
A21: 76664-37050-DT | B21: Aurea Corradino | C21: acorradinoj@harvard.edu | D21: +1 (646) 202-5965 | E21: 698 Canary Terrace | F21: New York City | G21: United States | H21: 10060 | I21: Yes
A22: 84565-53984-SX | B22: Kendal Scardefield | C22: UNKNOWN | D22: +353 (733) 405-3302 | E22: 3 Northridge Crossing | F22: Clondalkin | G22: Ireland | H22: D24 | I22: Yes
A23: 03090-88267-BQ | B23: Avrit Davidowsky | C23: adavidowskyl@netvibes.com | D23: +1 (616) 481-9962 | E23: 9 Warrior Junction | F23: Grand Rapids | G23: United States | H23: 49560 | I23: No
A24: 37651-47492-NC | B24: Annabel Antuk | C24: aantukm@kickstarter.com | D24: +1 (941) 740-6268 | E24: 77965 Lawn Park | F24: Punta Gorda | G24: United States | H24: 33982 | I24: Yes
A25: 95399-57205-HI | B25: Iorgo Kleinert | C25: ikleinertn@timesonline.co.uk | D25: +1 (360) 352-6598 | E25: 1 Morningstar Lane | F25: Vancouver | G25: United States | H25: 98682 | I25: Yes
A26: 24010-66714-HW | B26: Chrisy Blofeld | C26: cblofeldo@amazon.co.uk | D26: +1 (303) 936-3357 | E26: 013 Talisman Terrace | F26: Englewood | G26: United States | H26: 80150 | I26: No
A27: 07591-92789-UA | B27: Culley Farris | C27: UNKNOWN | D27: +1 (941) 267-4822 | E27: 4 Mitchell Drive | F27: Punta Gorda | G27: United States | H27: 33982 | I27: Yes
A28: 49231-44455-IC | B28: Selene Shales | C28: sshalesq@umich.edu | D28: +1 (707) 881-5004 | E28: 74 Bultman Plaza | F28: Petaluma | G28: United States | H28: 94975 | I28: Yes
A29: 50124-88608-EO | B29: Vivie Danneil | C29: vdanneilr@mtv.com | D29: +353 (751) 346-0399 | E29: 5626 Darwin Avenue | F29: Tralee | G29: Ireland | H29: V92 | I29: No
A30: 00888-74814-UZ | B30: Theresita Newbury | C30: tnewburys@usda.gov | D30: +353 (803) 587-0026 | E30: 79526 Bultman Lane | F30: Clonskeagh | G30: Ireland | H30: D04 | I30: No
A31: 14158-30713-OB | B31: Mozelle Calcutt | C31: mcalcuttt@baidu.com | D31: +353 (928) 869-1762 | E31: 4389 Russell Way | F31: Rathwire | G31: Ireland | H31: Y25 | I31: Yes
A32: 51427-89175-QJ | B32: Adrian Swaine | C32: UNKNOWN | D32: +1 (303) 486-9517 | E32: 95 Straubel Hill | F32: Aurora | G32: United States | H32: 80044 | I32: No
A33: 52082-49024-ON | B33: Ray Leivesley | C33: rleivesleyv@canalblog.com | D33: +1 (212) 535-7791 | E33: 91 Stephen Drive | F33: Jamaica | G33: United States | H33: 11407 | I33: No
A34: 04540-43685-DV | B34: Nelly Basezzi | C34: nbasezziw@webeden.co.uk | D34: +353 (125) 815-7345 | E34: 923 Mallard Junction | F34: Bailieborough | G34: Ireland | H34: C15 | I34: Yes
A35: 39123-12846-YJ | B35: Gallard Gatheral | C35: ggatheralx@123-reg.co.uk | D35: UNKNOWN | E35: 40 Clemons Place | F35: Grand Forks | G35: United States | H35: 58207 | I35: No
A36: 44981-99666-XB | B36: Una Welberry | C36: uwelberryy@ebay.co.uk | D36: +44 (392) 503-8132 | E36: 40915 Schlimgen Park | F36: Upton | G36: United Kingdom | H36: DN21 | I36: Yes
A37: 24825-51803-CQ | B37: Faber Eilhart | C37: feilhartz@who.int | D37: +1 (304) 510-6095 | E37: 6966 Victoria Street | F37: Charleston | G37: United States | H37: 25362 | I37: No
A38: 77634-13918-GJ | B38: Zorina Ponting | C38: zponting10@altervista.org | D38: +1 (501) 172-1476 | E38: 7118 Holmberg Court | F38: Little Rock | G38: United States | H38: 72204 | I38: No
A39: 13694-25001-LX | B39: Silvio Strase | C39: sstrase11@booking.com | D39: +1 (303) 579-8015 | E39: 5 Forest Lane | F39: Denver | G39: United States | H39: 80291 | I39: No
A40: 08523-01791-TI | B40: Dorie de la Tremoille | C40: dde12@unesco.org | D40: +1 (612) 492-5160 | E40: 0817 Dennis Street | F40: Minneapolis | G40: United States | H40: 55458 | I40: No
A41: 49860-68865-AB | B41: Hy Zanetto | C41: UNKNOWN | D41: UNKNOWN | E41: 469 Paget Place | F41: Tucson | G41: United States | H41: 85715 | I41: Yes
A42: 21240-83132-SP | B42: Jessica McNess | C42: UNKNOWN | D42: +1 (504) 545-1478 | E42: 664 Erie Place | F42: New Orleans | G42: United States | H42: 70116 | I42: No
A43: 08350-81623-TF | B43: Lorenzo Yeoland | C43: lyeoland15@pbs.org | D43: +1 (860) 576-2887 | E43: 8510 Merrick Road | F43: Hartford | G43: United States | H43: 6183 | I43: Yes
A44: 73284-01385-SJ | B44: Abigail Tolworthy | C44: atolworthy16@toplist.cz | D44: +1 (801) 722-4425 | E44: 74 Shopko Way | F44: Ogden | G44: United States | H44: 84409 | I44: Yes
A45: 04152-34436-IE | B45: Maurie Bartol | C45: UNKNOWN | D45: +1 (617) 493-7594 | E45: 7625 Starling Court | F45: Boston | G45: United States | H45: 2216 | I45: No
A46: 06631-86965-XP | B46: Olag Baudassi | C46: obaudassi18@seesaa.net | D46: +1 (585) 356-6251 | E46: 55 Dottie Court | F46: Rochester | G46: United States | H46: 14604 | I46: Yes
A47: 54619-08558-ZU | B47: Petey Kingsbury | C47: pkingsbury19@comcast.net | D47: +1 (917) 705-8224 | E47: 28 Loftsgordon Place | F47: Bronx | G47: United States | H47: 10469 | I47: No
A48: 85589-17020-CX | B48: Donna Baskeyfied | C48: UNKNOWN | D48: +1 (205) 923-1460 | E48: 7586 Logan Avenue | F48: Birmingham | G48: United States | H48: 35205 | I48: Yes
... A52: 45089-52817-WN | B52: Inger Bouldon | C52: ibouldon1e@gizmodo.com | D52: +1 (754) 391-4736 | E52: 925 Barby Circle | F52: Fort Lauderdale | G52: United States | H52: 33355 | I52: No
A53: 76447-50326-IC | B53: Karry Flanders | C53: kflanders1f@over-blog.com | D53: +353 (467) 720-7274 | E53: 88 Blue Bill Park Avenue | F53: Crumlin | G53: Ireland | H53: D6W | I53: Yes
A54: 26333-67911-OL | B54: Hartley Mattioli | C54: hmattioli1g@webmd.com | D54: UNKNOWN | E54: 126 Valley Edge Street | F54: Kinloch | G54: United Kingdom | H54: PH43 | I54: No
A55: 40768-49176-BL | B55: Horatio Rubberts | C55: hrubberts1h@google.com.hk | D55: +1 (801) 635-8791 | E55: 459 Russell Center | F55: Provo | G55: United States | H55: 84605 | I55: No
A56: 22107-86640-SB | B56: Archambault Gillard | C56: agillard1i@issuu.com | D56: +1 (419) 663-2236 | E56: 97490 Susan Avenue | F56: Toledo | G56: United States | H56: 43666 | I56: No
A57: 09960-34242-LZ | B57: Salomo Cushworth | C57: UNKNOWN | D57: +1 (609) 409-7044 | E57: 44 Oneill Parkway | F57: Trenton | G57: United States | H57: 8650 | I57: No
A58: 04671-85591-RT | B58: Theda Grizard | C58: tgrizard1k@odnoklassniki.ru | D58: +1 (813) 243-2150 | E58: 6 Knutson Pass | F58: Tampa | G58: United States | H58: 33686 | I58: Yes
A59: 25729-68859-UA | B59: Rozele Relton | C59: rrelton1l@stanford.edu | D59: +1 (850) 626-1181 | E59: 2484 Reindahl Court | F59: Pensacola | G59: United States | H59: 32590 | I59: No
A60: 05501-86351-NX | B60: Willa Rolling | C60: UNKNOWN | D60: +1 (813) 759-3534 | E60: 3 Mockingbird Plaza | F60: Zephyrhills | G60: United States | H60: 33543 | I60: Yes
A61: 04521-04300-OK | B61: Stanislaus Gilroy | C61: sgilroy1n@eepurl.com | D61: UNKNOWN | E61: 9120 Harbort Terrace | F61: Saint Paul | G61: United States | H61: 55123 | I61: Yes
A62: 58689-55264-VK | B62: Correy Cottingham | C62: ccottingham1o@wikipedia.org | D62: +1 (260) 764-1820 | E62: 394 Logan Road | F62: Fort Wayne | G62: United States | H62: 46862 | I62: No
A63: 79436-73011-MM | B63: Pammi Endacott | C63: UNKNOWN | D63: +44 (177) 260-5076 | E63: 5841 Atwood Lane | F63: Wootton | G63: United Kingdom | H63: NN4 | I63: Yes
A64: 65552-60476-KY | B64: Nona Linklater | C64: UNKNOWN | D64: +1 (239) 347-9766 | E64: 856 Bonner Parkway | F64: Naples | G64: United States | H64: 34114 | I64: Yes
A65: 69904-02729-YS | B65: Annadiane Dykes | C65: adykes1r@eventbrite.com | D65: +1 (312) 111-6203 | E65: 31 Northport Terrace | F65: Chicago | G65: United States | H65: 60681 | I65: No
A66: 01433-04270-AX | B66: Felecia Dodgson | C66: UNKNOWN | D66: +1 (973) 434-8662 | E66: 48053 8th Crossing | F66: Newark | G66: United States | H66: 7104 | I66: Yes
A67: 14204-14186-LA | B67: Angelia Cockrem | C67: acockrem1t@engadget.com | D67: +1 (571) 316-8217 | E67: 1 Sherman Alley | F67: Vienna | G67: United States | H67: 22184 | I67: Yes
A68: 32948-34398-HC | B68: Belvia Umpleby | C68: bumpleby1u@soundcloud.com | D68: +1 (682) 627-0888 | E68: 710 Prairie Rose Terrace | F68: Fort Worth | G68: United States | H68: 76178 | I68: Yes
A69: 77343-52608-FF | B69: Nat Saleway | C69: nsaleway1v@dedecms.com | D69: +1 (323) 473-0294 | E69: 0780 Anthes Plaza | F69: Burbank | G69: United States | H69: 91505 | I69: No
A70: 42770-36274-QA | B70: Hayward Goulter | C70: hgoulter1w@abc.net.au | D70: +1 (423) 764-7751 | E70: 2081 Mariners Cove Drive | F70: Kingsport | G70: United States | H70: 37665 | I70: No
A71: 14103-58987-ZU | B71: Gay Rizzello | C71: grizzello1x@symantec.com | D71: +44 (247) 225-8003 | E71: 21 Schmedeman Crossing | F71: Liverpool | G71: United Kingdom | H71: L33 | I71: Yes
A72: 69958-32065-SW | B72: Shannon List | C72: slist1y@mapquest.com | D72: +1 (614) 279-9816 | E72: 7123 Algoma Center | F72: Columbus | G72: United States | H72: 43231 | I72: No
A73: 69533-84907-FA | B73: Shirlene Edmondson | C73: sedmondson1z@theguardian.com | D73: +353 (248) 428-7978 | E73: 4752 International Point | F73: Newmarket on Fergus | G73: Ireland | H73: P17 | I73: No
A74: 76005-95461-CI | B74: Aurlie McCarl | C74: UNKNOWN | D74: +1 (504) 209-2724 | E74: 731 David Park | F74: New Orleans | G74: United States | H74: 70183 | I74: No
A75: 15395-90855-VB | B75: Alikee Carryer | C75: UNKNOWN | D75: +1 (704) 799-5219 | E75: 247 Helena Drive | F75: Charlotte | G75: United States | H75: 28230 | I75: Yes
A76: 80640-45811-LB | B76: Jennifer Rangall | C76: jrangall22@newsvine.com | D76: +1 (781) 512-6637 | E76: 0 Grasskamp Lane | F76: Springfield | G76: United States | H76: 1114 | I76: Yes
A77: 28476-04082-GR | B77: Kipper Boorn | C77: kboorn23@ezinearticles.com | D77: +353 (359) 134-1550 | E77: 9513 Meadow Ridge Parkway | F77: Listowel | G77: Ireland | H77: V31 | I77: Yes
A78: 12018-75670-EU | B78: Melania Beadle | C78: UNKNOWN | D78: +353 (569) 458-9673 | E78: 4418 Quincy Terrace | F78: Moycullen | G78: Ireland | H78: A41 | I78: Yes
A79: 86437-17399-FK | B79: Colene Elgey | C79: celgey25@webs.com | D79: +1 (432) 261-0702 | E79: 45 Marcy Crossing | F79: Midland | G79: United States | H79: 79705 | I79: No
A80: 62979-53167-ML | B80: Lothaire Mizzi | C80: lmizzi26@rakuten.co.jp | D80: +1 (214) 719-8530 | E80: 74 Atwood Lane | F80: Dallas | G80: United States | H80: 75323 | I80: Yes
A81: 54810-81899-HL | B81: Cletis Giacomazzo | C81: cgiacomazzo27@jigsy.com | D81: +1 (571) 703-2064 | E81: 817 Ridgeway Hill | F81: Dulles | G81: United States | H81: 20189 | I81: No
A82: 26103-41504-IB | B82: Ami Arnow | C82: aarnow28@arizona.edu | D82: +1 (650) 238-1964 | E82: 12 Oakridge Court | F82: Oakland | G82: United States | H82: 94627 | I82: Yes
A83: 76534-45229-SG | B83: Sheppard Yann | C83: syann29@senate.gov | D83: +1 (719) 803-5276 | E83: 4 Farmco Place | F83: Colorado Springs | G83: United States | H83: 80930 | I83: Yes
A84: 81744-27332-RR | B84: Bunny Naulls | C84: bnaulls2a@tiny.cc | D84: +353 (809) 128-0755 | E84: 595 Melby Avenue | F84: Adare | G84: Ireland | H84: H54 | I84: Yes
A85: 91513-75657-PH | B85: Hally Lorait | C85: UNKNOWN | D85: +1 (716) 869-3749 | E85: 80 Jana Avenue | F85: Buffalo | G85: United States | H85: 14205 | I85: Yes
A86: 30373-66619-CB | B86: Zaccaria Sherewood | C86: zsherewood2c@apache.org | D86: +1 (209) 433-7924 | E86: 1325 Jay Terrace | F86: Fresno | G86: United States | H86: 93715 | I86: No
A87: 31582-23562-FM | B87: Jeffrey Dufaire | C87: jdufaire2d@fc2.com | D87: UNKNOWN | E87: 8 Buell Junction | F87: Fort Worth | G87: United States | H87: 76121 | I87: No
A88: 58638-01029-CB | B88: Blancha McAmish | C88: bmcamish2e@tripadvisor.com | D88: UNKNOWN | E88: 5484 Stephen Court | F88: Oklahoma City | G88: United States | H88: 73179 | I88: Yes
A89: 81431-12577-VD | B89: Beitris Keaveney | C89: bkeaveney2f@netlog.com | D89: UNKNOWN | E89: 67319 Redwing Parkway | F89: Beaumont | G89: United States | H89: 77705 | I89: No
A90: 68894-91205-MP | B90: Elna Grise | C90: egrise2g@cargocollective.com | D90: UNKNOWN | E90: 92 Becker Circle | F90: Reno | G90: United States | H90: 89519 | I90: No
A91: 87602-55754-VN | B91: Torie Gottelier | C91: tgottelier2h@vistaprint.com | D91: +1 (816) 743-8492 | E91: 426 Division Avenue | F91: Kansas City | G91: United States | H91: 64136 | I91: No
A92: 39181-35745-WH | B92: Loydie Langlais | C92: UNKNOWN | D92: +353 (576) 222-5069 | E92: 290 Ilene Street | F92: Crumlin | G92: Ireland | H92: D6W | I92: Yes
A93: 30381-64762-NG | B93: Adham Greenhead | C93: agreenhead2j@dailymail.co.uk | D93: +1 (951) 797-0738 | E93: 0062 Spenser Place | F93: Corona | G93: United States | H93: 92878 | I93: No
A94: 17503-27693-ZH | B94: Hamish MacSherry | C94: UNKNOWN | D94: +1 (512) 430-4374 | E94: 7 Brentwood Plaza | F94: Austin | G94: United States | H94: 78759 | I94: Yes
A95: 89442-35633-HJ | B95: Else Langcaster | C95: elangcaster2l@spotify.com | D95: +44 (547) 590-3103 | E95: 3658 Jenna Street | F95: Normanton | G95: United Kingdom | H95: LE15 | I95: Yes
A96: 13654-85265-IL | B96: Rudy Farquharson | C96: UNKNOWN | D96: UNKNOWN | E96: 30178 Claremont Road | F96: Charlesland | G96: Ireland | H96: A63 | I96: Yes
A97: 40946-22090-FP | B97: Norene Magauran | C97: nmagauran2n@51.la | D97: UNKNOWN | E97: 567 Artisan Place | F97: Fresno | G97: United States | H97: 93762 | I97: No
A98: 29050-93691-TS | B98: Vicki Kirdsch | C98: vkirdsch2o@google.fr | D98: UNKNOWN | E98: 0263 Golf Street | F98: Saint Louis | G98: United States | H98: 63150 | I98: No
A99: 64395-74865-WF | B99: Ilysa Whapple | C99: iwhapple2p@com.com | D99: +1 (559) 522-1152 | E99: 41598 Everett Drive | F99: Fresno | G99: United States | H99: 93726 | I99: No
A100: 81861-66046-SU | B100: Ruy Cancellieri | C100: UNKNOWN | D100: +353 (338) 743-8327 | E100: 251 Welch Parkway | F100: Confey | G100: Ireland | H100: A86 | I100: No
A101: 13366-78506-KP | B101: Aube Follett | C101: UNKNOWN | D101: +1 (614) 370-6392 | E101: 8671 David Park | F101: Columbus | G101: United States | H101: 43210 | I101: Yes
A102: 08847-29858-HN | B102: Rudiger Di Bartolomeo | C102: UNKNOWN | D102: +1 (209) 148-6668 | E102: 7700 Melby Park | F102: Stockton | G102: United States | H102: 95205 | I102: Yes
A103: 00539-42510-RY | B103: Nickey Youles | C103: nyoules2t@reference.com | D103: +353 (641) 846-7654 | E103: 12461 Dryden Pass | F103: Edgeworthstown | G103: Ireland | H103: E25 | I103: Yes
...

Sheet Products
A1: Product ID | B1: Coffee Type | C1: Roast Type | D1: Size | E1: Unit Price | F1: Price per 100g | G1: Profit
A2: A-L-0.2 | B2: Arabica | C2: Light | D2: 0.2 | E2: 3.885 | F2: 1.9425 | G2: 0.34965
A3: A-L-0.5 | B3: Arabica | C3: Light | D3: 0.5 | E3: 7.77 | F3: 1.554 | G3: 0.6993
A4: A-L-1 | B4: Arabica | C4: Light | D4: 1 | E4: 12.95 | F4: 1.295 | G4: 1.1655
A5: A-L-2.5 | B5: Arabica | C5: Light | D5: 2.5 | E5: 29.785 | F5: 1.1914 | G5: 2.68065
A6: A-M-0.2 | B6: Arabica | C6: Medium | D6: 0.2 | E6: 3.375 | F6: 1.6875 | G6: 0.30375
A7: A-M-0.5 | B7: Arabica | C7: Medium | D7: 0.5 | E7: 6.75 | F7: 1.35 | G7: 0.6075
A8: A-M-1 | B8: Arabica | C8: Medium | D8: 1 | E8: 11.25 | F8: 1.125 | G8: 1.0125
A9: A-M-2.5 | B9: Arabica | C9: Medium | D9: 2.5 | E9: 25.875 | F9: 1.035 | G9: 2.32875
A10: A-D-0.2 | B10: Arabica | C10: Dark | D10: 0.2 | E10: 2.985 | F10: 1.4925 | G10: 0.26865
A11: A-D-0.5 | B11: Arabica | C11: Dark | D11: 0.5 | E11: 5.97 | F11: 1.194 | G11: 0.5373
A12: A-D-1 | B12: Arabica | C12: Dark | D12: 1 | E12: 9.95 | F12: 0.995 | G12: 0.8955
A13: A-D-2.5 | B13: Arabica | C13: Dark | D13: 2.5 | E13: 22.885 | F13: 0.9154 | G13: 2.05965
... A49: E-D-2.5 | B49: Excelsa | C49: Dark | D49: 2.5 | E49: 27.945 | F49: 1.1178 | G49: 3.07395
